whispyrx/__init__.py
whispyrx/app.py
whispyrx-1.0.2.dist-info/licenses/LICENSE
whispyrx-1.0.2.dist-info/METADATA
whispyrx-1.0.2.dist-info/WHEEL
whispyrx-1.0.2.dist-info/entry_points.txt
whispyrx-1.0.2.dist-info/top_level.txt
whispyrx-1.0.2.dist-info/RECORD
