Metadata-Version: 2.4
Name: WhispyrX
Version: 1.0.2
Summary: A peer-to-peer TUI chat app using Textual
Home-page: https://pypi.org/project/WhispyrX/
Author: MOHAMMAD SHAHARIAR AHMMED SHOVON
Author-email: shovonali885@proton.me
Classifier: Programming Language :: Python :: 3
Classifier: License :: OSI Approved :: MIT License
Classifier: Operating System :: OS Independent
Classifier: Development Status :: 5 - Production/Stable
Classifier: Environment :: Console
Classifier: Intended Audience :: Developers
Classifier: Topic :: Communications :: Chat
Requires-Python: >=3.9
License-File: LICENSE
Requires-Dist: textual
Requires-Dist: httpx
Requires-Dist: requests
Requires-Dist: sseclient
Requires-Dist: emoji
Dynamic: author
Dynamic: author-email
Dynamic: classifier
Dynamic: description
Dynamic: description-content-type
Dynamic: home-page
Dynamic: license-file
Dynamic: requires-dist
Dynamic: requires-python
Dynamic: summary
